udp/__init__.py
udp/aio.py
udp/channel.py
udp/hub.py
udp/startrek.py
udp/ba/__init__.py
udp/ba/array.py
udp/ba/convert.py
udp/ba/data.py
udp/ba/helper.py
udp/ba/integer.py
udp/ba/mutable.py
udp/ba/utils.py
udp/mtp/__init__.py
udp/mtp/header.py
udp/mtp/package.py
udp/mtp/packer.py
udp/mtp/protocol.py
udp-2.2.2.dist-info/METADATA
udp-2.2.2.dist-info/WHEEL
udp-2.2.2.dist-info/top_level.txt
udp-2.2.2.dist-info/RECORD
